stginga/__init__.py
stginga/_astropy_init.py
stginga/gingawrapper.py
stginga/plugin_info.py
stginga/utils.py
stginga/version.py
stginga/data/dqflags_acs.txt
stginga/data/dqflags_hstgen.txt
stginga/data/dqflags_jwst.txt
stginga/data/dqflags_wfc3.txt
stginga/examples/configs/channel_Image.cfg
stginga/examples/configs/general.cfg
stginga/examples/configs/ginga_config.py
stginga/examples/configs/plugin_BackgroundSub.cfg
stginga/examples/configs/plugin_BadPixCorr.cfg
stginga/examples/configs/plugin_Contents.cfg
stginga/examples/configs/plugin_DQInspect.cfg
stginga/examples/configs/plugin_Mosaic.cfg
stginga/examples/configs/plugin_SNRCalc.cfg
stginga/examples/configs/plugin_Thumbs.cfg
stginga/plugins/BackgroundSub.py
stginga/plugins/BadPixCorr.py
stginga/plugins/DQInspect.py
stginga/plugins/MosaicAuto.py
stginga/plugins/SNRCalc.py
stginga/plugins/__init__.py
stginga/plugins/local_plugin_mixin.py
stginga/tests/__init__.py
stginga/tests/test_utils.py
stginga-1.6.0.dist-info/LICENSE.rst
stginga-1.6.0.dist-info/METADATA
stginga-1.6.0.dist-info/WHEEL
stginga-1.6.0.dist-info/entry_points.txt
stginga-1.6.0.dist-info/top_level.txt
stginga-1.6.0.dist-info/RECORD
